custom_user_roles-1.1.0.dist-info/DESCRIPTION.rst
custom_user_roles-1.1.0.dist-info/METADATA
custom_user_roles-1.1.0.dist-info/metadata.json
custom_user_roles-1.1.0.dist-info/RECORD
custom_user_roles-1.1.0.dist-info/top_level.txt
custom_user_roles-1.1.0.dist-info/WHEEL
userroles/__init__.py
userroles/decorators.py
userroles/models.py
userroles/tests.py
userroles/migrations/0001_initial.py
userroles/migrations/__init__.py
userroles/south_migrations/0001_initial.py
userroles/south_migrations/__init__.py
