Metadata-Version: 2.0
Name: custom-user-roles
Version: 1.1.0
Summary: Simple role-based user permissions for Django.
Home-page: https://github.com/laginha/django-user-roles
Author: Diogo Laginha
Author-email: diogo.laginha.machado@gmail.com
License: MIT
Platform: UNKNOWN
Classifier: License :: OSI Approved :: MIT License
Classifier: Programming Language :: Python :: 2
Classifier: Intended Audience :: Developers
Requires-Dist: django
Requires-Dist: milkman
